dnazip/__init__.py
dnazip/compress.py
dnazip/decompress.py
dnazip/tests.py
dnazip-0.1.2.data/scripts/dnazip
dnazip-0.1.2.dist-info/DESCRIPTION.rst
dnazip-0.1.2.dist-info/METADATA
dnazip-0.1.2.dist-info/RECORD
dnazip-0.1.2.dist-info/WHEEL
dnazip-0.1.2.dist-info/metadata.json
dnazip-0.1.2.dist-info/top_level.txt
