Metadata-Version: 2.0
Name: dnazip
Version: 0.1.2
Summary: Compression for Fasta files
Home-page: http://github.com/Bartvelp/dnazip
Author: Bart Grosman
Author-email: bart.grosman@wur.nl
License: MIT
Platform: UNKNOWN
